bf2pico/__init__.py
bf2pico/brewfather.py
bf2pico/brewplot.py
bf2pico/events.py
bf2pico/pico.py
bf2pico/prosaic.py
bf2pico/recipe.py
bf2pico/session.py
bf2pico/settings.py
bf2pico/webapp.py
bf2pico/zymatic_cli.py
bf2pico-1.5.0.dist-info/METADATA
bf2pico-1.5.0.dist-info/WHEEL
bf2pico-1.5.0.dist-info/entry_points.txt
bf2pico-1.5.0.dist-info/top_level.txt
bf2pico-1.5.0.dist-info/RECORD
