Metadata-Version: 2.1
Name: bf2pico
Version: 1.5.0
Summary: Convert Brewfather Recipes to Pico Brew Steps
Home-page: https://github.com/tmb28054/bf2pico
Author: Topaz Bott
Author-email: topaz@topazhome.net
License: Apache License 2.0
Platform: UNKNOWN
Classifier: Development Status :: 5 - Production/Stable
Classifier: Intended Audience :: Developers
Classifier: Natural Language :: English
Classifier: Programming Language :: Python
Classifier: Programming Language :: Python :: 3.8
Classifier: Programming Language :: Python :: 3.9
Classifier: Programming Language :: Python :: 3.10
Classifier: Programming Language :: Python :: 3.11
Requires-Dist: boto3
Requires-Dist: diskcache
Requires-Dist: flask
Requires-Dist: gunicorn
Requires-Dist: matplotlib
Requires-Dist: requests
Requires-Dist: tabulate
